drf_queryset_optimization/__init__.py
drf_queryset_optimization/mixins.py
drf_queryset_optimization-0.1.1.dist-info/METADATA
drf_queryset_optimization-0.1.1.dist-info/WHEEL
drf_queryset_optimization-0.1.1.dist-info/top_level.txt
drf_queryset_optimization-0.1.1.dist-info/RECORD
