Metadata-Version: 2.1
Name: drf-queryset-optimization
Version: 0.1.1
Summary: A package for optimizing querysets in Django REST Framework views and viewsets
Home-page: https://github.com/mahdirahimi1999/drf-queryset-optimization
Author: Mahdi Rahimi
Author-email: mahdi.rahimi95@gmail.com
Classifier: Development Status :: 3 - Alpha
Classifier: License :: OSI Approved :: MIT License
Classifier: Programming Language :: Python :: 3
Classifier: Programming Language :: Python :: 3.6
Classifier: Programming Language :: Python :: 3.7
Classifier: Programming Language :: Python :: 3.8
Classifier: Programming Language :: Python :: 3.9
Classifier: Framework :: Django
Classifier: Framework :: Django :: 2.2
Classifier: Framework :: Django :: 3.0
Classifier: Framework :: Django :: 3.1
Classifier: Intended Audience :: Developers
Classifier: Topic :: Software Development :: Libraries :: Python Modules
